dohlee/__init__.py
dohlee/__main__.py
dohlee/cli.py
dohlee/gene.py
dohlee/hg38.py
dohlee/plot.py
dohlee/fonts/HelveticaNeue.ttf
dohlee/fonts/__init__.py
dohlee-0.1.5.dist-info/METADATA
dohlee-0.1.5.dist-info/RECORD
dohlee-0.1.5.dist-info/WHEEL
dohlee-0.1.5.dist-info/entry_points.txt
dohlee-0.1.5.dist-info/top_level.txt
