Metadata-Version: 2.1
Name: dohlee
Version: 0.1.5
Summary: My personal python utility library.
Home-page: https://github.com/dohlee/python-dohlee
Author: Dohoon Lee
Author-email: apap950419@gmail.com
License: MIT license
Platform: UNKNOWN
Classifier: Development Status :: 5 - Production/Stable
Classifier: Intended Audience :: Developers
Classifier: License :: OSI Approved :: MIT License
Classifier: Operating System :: Unix
Classifier: Operating System :: POSIX
Classifier: Operating System :: Microsoft :: Windows
Classifier: Programming Language :: Python
Classifier: Programming Language :: Python :: 3
Classifier: Programming Language :: Python :: 3.5
Classifier: Programming Language :: Python :: 3.6
Classifier: Topic :: Utilities
Requires-Dist: matplotlib (==2.2.2)
Requires-Dist: numpy (==1.14.2)
Requires-Dist: pandas (==0.22.0)
Requires-Dist: scikit-learn (==0.19.1)
Requires-Dist: scipy (==1.0.1)
Requires-Dist: seaborn (==0.8.1)
Requires-Dist: six (==1.11.0)
Requires-Dist: sklearn (==0.0)
Requires-Dist: mygene (==3.0.0)
Requires-Dist: pyensembl (==1.2.6)
